[
 {
  "date": "2023-09-14T10:09:35Z",
  "kind": "author",
  "peers": [
   "machenbach@chromium.org",
   "jgruber@chromium.org"
  ],
  "additions": 2,
  "deletions": 1,
  "files": 1
 },
 {
  "date": "2024-09-04T14:06:37Z",
  "kind": "author",
  "peers": [
   "clemensb@chromium.org",
   "nicohartmann@chromium.org"
  ],
  "additions": 9,
  "deletions": 0,
  "files": 1
 },
 {
  "date": "2025-01-30T10:18:54Z",
  "kind": "author",
  "peers": [
   "bikineev@chromium.org",
   "mlippautz@chromium.org"
  ],
  "additions": 4,
  "deletions": 0,
  "files": 1
 },
 {
  "date": "2025-05-05T17:27:22Z",
  "kind": "author",
  "peers": [
   "nicohartmann@chromium.org",
   "olivf@chromium.org"
  ],
  "additions": 5,
  "deletions": 0,
  "files": 1
 },
 {
  "date": "2025-04-30T18:13:32Z",
  "kind": "author",
  "peers": [
   "olivf@chromium.org",
   "saelo@chromium.org"
  ],
  "additions": 40,
  "deletions": 9,
  "files": 3
 },
 {
  "date": "2025-06-27T01:22:00Z",
  "kind": "author",
  "peers": [
   "verwaest@chromium.org",
   "nikolaos@chromium.org"
  ],
  "additions": 7,
  "deletions": 0,
  "files": 1
 },
 {
  "date": "2025-09-18T17:55:31Z",
  "kind": "author",
  "peers": [
   "mfarazma@ibm.com",
   "leszeks@chromium.org"
  ],
  "additions": 1,
  "deletions": 1,
  "files": 1
 },
 {
  "date": "2025-10-10T05:55:19Z",
  "kind": "author",
  "peers": [
   "jgruber@chromium.org",
   "mfarazma@ibm.com",
   "nicohartmann@chromium.org"
  ],
  "additions": 46,
  "deletions": 44,
  "files": 3
 },
 {
  "date": "2025-10-16T13:35:55Z",
  "kind": "author",
  "peers": [
   "nicohartmann@chromium.org",
   "mfarazma@ibm.com"
  ],
  "additions": 10,
  "deletions": 10,
  "files": 1
 },
 {
  "date": "2025-11-06T00:34:07Z",
  "kind": "author",
  "peers": [
   "pthier@chromium.org",
   "manoskouk@chromium.org"
  ],
  "additions": 20,
  "deletions": 29,
  "files": 2
 },
 {
  "date": "2025-12-11T22:44:28Z",
  "kind": "author",
  "peers": [
   "jkummerow@chromium.org",
   "clemensb@chromium.org"
  ],
  "additions": 16,
  "deletions": 15,
  "files": 3
 },
 {
  "date": "2025-12-17T11:15:37Z",
  "kind": "author",
  "peers": [
   "verwaest@chromium.org",
   "leszeks@chromium.org"
  ],
  "additions": 32,
  "deletions": 11,
  "files": 5
 }
]