[
 {
  "date": "2024-11-08T07:37:46Z",
  "kind": "author",
  "peers": [],
  "additions": 6,
  "deletions": 12,
  "files": 4
 },
 {
  "date": "2024-11-06T08:10:37Z",
  "kind": "author",
  "peers": [],
  "additions": 152,
  "deletions": 1,
  "files": 2
 },
 {
  "date": "2025-02-27T07:48:55Z",
  "kind": "author",
  "peers": [],
  "additions": 13,
  "deletions": 7,
  "files": 2
 },
 {
  "date": "2025-03-10T09:13:33Z",
  "kind": "author",
  "peers": [],
  "additions": 1,
  "deletions": 1,
  "files": 1
 },
 {
  "date": "2025-05-19T21:13:08Z",
  "kind": "author",
  "peers": [],
  "additions": 38,
  "deletions": 16,
  "files": 3
 },
 {
  "date": "2025-05-19T19:03:55Z",
  "kind": "author",
  "peers": [],
  "additions": 83,
  "deletions": 0,
  "files": 1
 },
 {
  "date": "2025-08-04T08:54:50Z",
  "kind": "author",
  "peers": [],
  "additions": 448,
  "deletions": 5,
  "files": 11
 },
 {
  "date": "2025-09-11T06:49:06Z",
  "kind": "author",
  "peers": [],
  "additions": 42,
  "deletions": 30,
  "files": 8
 }
]