[
 {
  "date": "2020-04-28T11:42:26Z",
  "kind": "author",
  "peers": [
   "cbiesinger",
   "ikilpatrick"
  ],
  "additions": 200,
  "deletions": 5,
  "files": 11
 },
 {
  "date": "2020-04-28T11:34:00Z",
  "kind": "review",
  "peers": [
   "jkim"
  ],
  "additions": 13,
  "deletions": 0,
  "files": 1
 },
 {
  "date": "2020-04-28T11:28:42Z",
  "kind": "author",
  "peers": [
   "ikilpatrick"
  ],
  "additions": 245,
  "deletions": 0,
  "files": 7
 },
 {
  "date": "2020-04-28T11:25:12Z",
  "kind": "review",
  "peers": [
   "jkim"
  ],
  "additions": 36,
  "deletions": 0,
  "files": 1
 },
 {
  "date": "2019-10-24T17:04:37Z",
  "kind": "author",
  "peers": [
   "cbiesinger"
  ],
  "additions": 62,
  "deletions": 0,
  "files": 3
 },
 {
  "date": "2019-10-24T17:04:18Z",
  "kind": "author",
  "peers": [
   "atotic",
   "mstensho"
  ],
  "additions": 41,
  "deletions": 0,
  "files": 1
 },
 {
  "date": "2019-10-24T17:03:36Z",
  "kind": "author",
  "peers": [
   "mstensho"
  ],
  "additions": 43,
  "deletions": 0,
  "files": 1
 },
 {
  "date": "2019-07-24T12:34:26Z",
  "kind": "author",
  "peers": [
   "ikilpatrick"
  ],
  "additions": 156,
  "deletions": 0,
  "files": 4
 },
 {
  "date": "2019-07-24T12:33:58Z",
  "kind": "author",
  "peers": [
   "cbiesinger"
  ],
  "additions": 36,
  "deletions": 0,
  "files": 1
 },
 {
  "date": "2019-07-24T12:33:10Z",
  "kind": "author",
  "peers": [
   "atotic",
   "mstensho"
  ],
  "additions": 406,
  "deletions": 0,
  "files": 5
 },
 {
  "date": "2019-07-24T12:30:49Z",
  "kind": "review",
  "peers": [
   "cbiesinger"
  ],
  "additions": 26,
  "deletions": 0,
  "files": 1
 },
 {
  "date": "2019-07-24T12:30:23Z",
  "kind": "review",
  "peers": [
   "cbiesinger"
  ],
  "additions": 49,
  "deletions": 0,
  "files": 1
 },
 {
  "date": "2019-06-19T18:07:00Z",
  "kind": "review",
  "peers": [
   "cbiesinger"
  ],
  "additions": 51,
  "deletions": 0,
  "files": 1
 },
 {
  "date": "2019-06-19T18:06:34Z",
  "kind": "review",
  "peers": [
   "cbiesinger"
  ],
  "additions": 26,
  "deletions": 0,
  "files": 1
 },
 {
  "date": "2019-06-05T09:29:07Z",
  "kind": "review",
  "peers": [
   "cbiesinger"
  ],
  "additions": 22,
  "deletions": 0,
  "files": 2
 },
 {
  "date": "2019-06-05T09:28:15Z",
  "kind": "review",
  "peers": [
   "cbiesinger"
  ],
  "additions": 21,
  "deletions": 0,
  "files": 2
 },
 {
  "date": "2019-06-05T09:26:24Z",
  "kind": "author",
  "peers": [],
  "additions": 2,
  "deletions": 0,
  "files": 1
 },
 {
  "date": "2019-06-05T09:26:03Z",
  "kind": "author",
  "peers": [
   "mstensho"
  ],
  "additions": 61,
  "deletions": 0,
  "files": 1
 },
 {
  "date": "2019-06-05T09:25:04Z",
  "kind": "review",
  "peers": [
   "cbiesinger"
  ],
  "additions": 48,
  "deletions": 0,
  "files": 2
 },
 {
  "date": "2019-05-03T17:30:29Z",
  "kind": "review",
  "peers": [
   "cbiesinger"
  ],
  "additions": 55,
  "deletions": 0,
  "files": 1
 },
 {
  "date": "2019-04-24T10:31:42Z",
  "kind": "author",
  "peers": [
   "mstensho"
  ],
  "additions": 68,
  "deletions": 0,
  "files": 2
 },
 {
  "date": "2019-04-24T10:30:34Z",
  "kind": "review",
  "peers": [
   "pjh0718"
  ],
  "additions": 21,
  "deletions": 0,
  "files": 2
 },
 {
  "date": "2019-04-24T10:18:29Z",
  "kind": "author",
  "peers": [
   "mstensho"
  ],
  "additions": 34,
  "deletions": 0,
  "files": 1
 },
 {
  "date": "2019-04-23T14:06:47Z",
  "kind": "author",
  "peers": [
   "mstensho"
  ],
  "additions": 68,
  "deletions": 0,
  "files": 2
 },
 {
  "date": "2019-04-23T14:06:22Z",
  "kind": "review",
  "peers": [
   "pjh0718"
  ],
  "additions": 21,
  "deletions": 0,
  "files": 2
 },
 {
  "date": "2019-04-23T14:05:57Z",
  "kind": "author",
  "peers": [
   "mstensho"
  ],
  "additions": 34,
  "deletions": 0,
  "files": 1
 },
 {
  "date": "2019-04-01T13:43:14Z",
  "kind": "review",
  "peers": [
   "cbiesinger"
  ],
  "additions": 21,
  "deletions": 0,
  "files": 1
 },
 {
  "date": "2019-03-16T12:13:05Z",
  "kind": "author",
  "peers": [
   "mstensho"
  ],
  "additions": 134,
  "deletions": 0,
  "files": 5
 },
 {
  "date": "2019-03-15T18:09:28Z",
  "kind": "author",
  "peers": [
   "mstensho"
  ],
  "additions": 134,
  "deletions": 0,
  "files": 5
 },
 {
  "date": "2019-02-07T21:50:22Z",
  "kind": "author",
  "peers": [
   "cbiesinger"
  ],
  "additions": 42,
  "deletions": 0,
  "files": 1
 },
 {
  "date": "2019-02-05T17:53:39Z",
  "kind": "author",
  "peers": [
   "cbiesinger"
  ],
  "additions": 42,
  "deletions": 0,
  "files": 1
 },
 {
  "date": "2018-07-11T07:04:58Z",
  "kind": "review",
  "peers": [
   "mstensho"
  ],
  "additions": 36,
  "deletions": 0,
  "files": 2
 },
 {
  "date": "2018-07-11T06:58:03Z",
  "kind": "author",
  "peers": [
   "mstensho"
  ],
  "additions": 27,
  "deletions": 6,
  "files": 6
 },
 {
  "date": "2018-05-18T10:15:13Z",
  "kind": "author",
  "peers": [
   "kojii",
   "mstensho",
   "robertma"
  ],
  "additions": 102,
  "deletions": 0,
  "files": 3
 },
 {
  "date": "2018-04-20T20:59:00Z",
  "kind": "review",
  "peers": [
   "mstensho"
  ],
  "additions": 37,
  "deletions": 0,
  "files": 2
 },
 {
  "date": "2018-04-15T07:35:53Z",
  "kind": "review",
  "peers": [
   "mstensho"
  ],
  "additions": 27,
  "deletions": 0,
  "files": 2
 },
 {
  "date": "2018-04-15T07:35:14Z",
  "kind": "review",
  "peers": [
   "wangxianzhu"
  ],
  "additions": 169,
  "deletions": 0,
  "files": 6
 },
 {
  "date": "2018-03-31T21:30:21Z",
  "kind": "author",
  "peers": [
   "mstensho"
  ],
  "additions": 294,
  "deletions": 0,
  "files": 6
 },
 {
  "date": "2018-03-31T21:28:44Z",
  "kind": "author",
  "peers": [
   "mstensho"
  ],
  "additions": 94,
  "deletions": 0,
  "files": 3
 },
 {
  "date": "2018-03-31T21:19:05Z",
  "kind": "author",
  "peers": [
   "mstensho"
  ],
  "additions": 76,
  "deletions": 0,
  "files": 2
 },
 {
  "date": "2025-05-12T09:21:50Z",
  "kind": "review",
  "peers": [
   "ikilpatrick"
  ],
  "additions": 10,
  "deletions": 0,
  "files": 1
 },
 {
  "date": "2025-05-12T09:16:14Z",
  "kind": "review",
  "peers": [
   "ikilpatrick"
  ],
  "additions": 118,
  "deletions": 0,
  "files": 4
 },
 {
  "date": "2025-05-14T15:58:25Z",
  "kind": "review",
  "peers": [
   "ikilpatrick"
  ],
  "additions": 7,
  "deletions": 0,
  "files": 1
 },
 {
  "date": "2025-05-23T19:13:10Z",
  "kind": "author",
  "peers": [
   "ikilpatrick"
  ],
  "additions": 33,
  "deletions": 45,
  "files": 13
 }
]