{"tests/wpt/tests/css/css-speech/speak-as":{"WEB_FEATURES.yml":{"r":[412,[1]],"f":1},"speak-as-digits-001-manual.html":{"r":[286,[1]],"f":1},"speak-as-digits-002-manual.html":{"r":[286,[1]],"f":1},"speak-as-literal-punctuation-001-manual.html":{"r":[286,[1]],"f":1},"speak-as-spell-out-001-manual.html":{"r":[286,[1]],"f":1}},"tests/wpt/meta-legacy-layout/html/browsers/browsing-the-web/unloading-documents/unload":{"003.html.ini":{"r":[285,[1],375,[1]],"d":1741850817000,"f":1},"006.html.ini":{"r":[285,[1],375,[1]],"d":1741850817000,"f":1},"unload-main-frame-cross-origin.window.js.ini":{"r":[285,[1],330,[1,1],375,[1]],"d":1741850817000,"f":1},"unload-main-frame-same-origin.window.js.ini":{"r":[285,[1],330,[1,1],375,[1]],"d":1741850817000,"f":1}},"tests/wpt/meta-legacy-layout/referrer-policy/gen/iframe.http-rp/strict-origin-when-cross-origin":{"sharedworker-classic.http.html.ini":{"r":[285,[1],375,[1]],"d":1741850817000,"f":1},"sharedworker-module.http.html.ini":{"r":[285,[1],375,[1]],"d":1741850817000,"f":1},"fetch.http.html.ini":{"r":[285,[1],357,[1]],"d":1731050363000,"f":1}},"tests/wpt/tests/tools/third_party/h2/docs/source/_templates":{".gitkeep":{"r":[306,[1]],"f":1}},"tests/wpt/web-platform-tests/tools/wave/www":{"comparison.html":{"r":[183,[1],286,[1]],"d":1687769310000,"f":1},"configuration.html":{"r":[183,[1],286,[1]],"d":1687769310000,"f":1},"css":{"r":[183,[1],286,[1]],"d":1687769310000},"favicon.ico":{"r":[183,[1],286,[1]],"d":1687769310000,"f":1},"finish.html":{"r":[183,[1],286,[1]],"d":1687769310000,"f":1},"index.html":{"r":[183,[1],286,[1]],"d":1687769310000,"f":1},"lib":{"r":[183,[1],286,[1]],"d":1687769310000},"newsession.html":{"r":[183,[1],286,[1]],"d":1687769310000,"f":1},"next.html":{"r":[183,[1],286,[1]],"d":1687769310000,"f":1},"overview.html":{"r":[183,[1],286,[1]],"d":1687769310000,"f":1},"pause.html":{"r":[183,[1],286,[1]],"d":1687769310000,"f":1},"res":{"r":[183,[1],286,[1]],"d":1687769310000},"results.html":{"r":[183,[1],286,[1]],"d":1687769310000,"f":1},"submitresult.html":{"r":[183,[1],286,[1]],"d":1687769310000,"f":1},"test.html":{"r":[286,[1]],"d":1687769310000,"f":1},"webfonts":{"r":[183,[1],286,[1]],"d":1687769310000}},"tests/wpt/metadata/referrer-policy/no-referrer-when-downgrade/http-rp/same-origin/http-https/script-tag/no-redirect":{"upgrade-protocol.http.html.ini":{"r":[90,[2]],"d":1569429545000,"f":1}},"tests/wpt/metadata/referrer-policy/strict-origin-when-cross-origin/attr-referrer/same-origin":{"http-http":{"r":[0,[3],5,[1],27,[1],46,[1,0,0,0,2],90,[2]],"d":1569429545000},"http-https":{"r":[0,[3],5,[1],27,[1],46,[1,0,0,0,1],90,[2]],"d":1569429545000}}}