[
 {
  "date": "2021-01-21T12:47:01Z",
  "kind": "author",
  "peers": [],
  "additions": 14,
  "deletions": 14,
  "files": 4
 },
 {
  "date": "2020-10-01T00:12:00Z",
  "kind": "author",
  "peers": [],
  "additions": 1,
  "deletions": 1,
  "files": 1
 },
 {
  "date": "2020-09-23T11:47:01Z",
  "kind": "author",
  "peers": [],
  "additions": 135,
  "deletions": 18,
  "files": 3
 },
 {
  "date": "2020-09-23T11:46:59Z",
  "kind": "author",
  "peers": [],
  "additions": 1,
  "deletions": 0,
  "files": 1
 },
 {
  "date": "2020-09-21T17:41:34Z",
  "kind": "author",
  "peers": [],
  "additions": 135,
  "deletions": 18,
  "files": 3
 },
 {
  "date": "2020-09-21T17:41:26Z",
  "kind": "author",
  "peers": [],
  "additions": 1,
  "deletions": 0,
  "files": 1
 },
 {
  "date": "2015-06-07T15:47:14Z",
  "kind": "author",
  "peers": [],
  "additions": 8,
  "deletions": 7,
  "files": 2
 },
 {
  "date": "2015-03-16T17:42:59Z",
  "kind": "author",
  "peers": [],
  "additions": 8,
  "deletions": 4,
  "files": 2
 }
]