{"Source/ThirdParty/ANGLE/src/tests/deqp_support":{"deqp_egl_test_expectations.txt":{"r":[239,[1,1],245,[1],274,[1],287,[1],292,[1,0,0,0,1,0,0,0,1],322,[1,1,0,0,2],336,[1,0,1],343,[1],349,[3],367,[1,0,0,1],382,[1],421,[1]],"f":1},"deqp_gles2_test_expectations.txt":{"r":[239,[1],255,[1],264,[1],272,[1,0,1,0,0,1],287,[1],296,[1],303,[1],309,[1],314,[2,0,0,0,1],323,[1,0,0,1],335,[1,0,0,1],343,[1,2,1,0,2,1,1,0,0,0,1,0,0,1],367,[1,0,0,1],381,[1],386,[1],393,[1],400,[1],421,[1]],"f":1},"deqp_gles31_test_expectations.txt":{"r":[239,[1,1,0,1,0,0,1,0,1],255,[1],264,[1,1],272,[1],287,[1],296,[1],307,[1],318,[1,0,0,0,1,1,0,0,1],335,[1,0,0,1],343,[1],370,[1],381,[1,1],400,[1],421,[1]],"f":1},"deqp_gles3_test_expectations.txt":{"r":[239,[1],245,[1],264,[1],272,[1,0,1],287,[1],292,[1,0,0,0,1],303,[1],309,[1,1,0,0,0,2],322,[1,1,0,0,1],335,[1,0,0,1],343,[1],353,[1],359,[1],367,[1],381,[1,1],418,[1,0,0,1]],"f":1},"deqp_khr_gles31_test_expectations.txt":{"r":[239,[1,1],245,[1],255,[1],265,[1,1],272,[1],287,[1],292,[1],322,[1,1,0,0,1],336,[1,0,1],343,[1,0,0,1,2,1,4,0,0,0,1,0,1,0,0,0,1,0,1],367,[1,0,0,1],381,[1,1],421,[1]],"f":1},"deqp.gni":{"r":[100,[1],118,[1,0,0,0,1,1,1],134,[1],150,[1,0,2],205,[1],216,[1],234,[1],240,[1],247,[1],264,[1],287,[1],292,[1],302,[1],326,[2,0,0,1],335,[1,1],343,[1,0,0,0,2,1],353,[1,0,1],361,[1],367,[1,0,0,0,1],386,[1,2],393,[1],420,[1]],"f":1},"deqp_khr_glesext_test_expectations.txt":{"r":[400,[1],418,[1]],"f":1},"angle_deqp_gtest.cpp":{"r":[0,[1],70,[1],88,[3,0,0,0,1],100,[1],107,[2,2,1],124,[1],134,[1],150,[1,0,2],205,[1],216,[1],234,[1],240,[1,0,1],264,[1],287,[1],292,[1],300,[1,0,1,1],314,[1,0,0,0,1],329,[1],338,[1],344,[2],353,[1],367,[1],400,[1]],"f":1},"tcuANGLENativeDisplayFactory.cpp":{"r":[0,[1],70,[1],88,[3,0,0,0,1],134,[1],150,[1,0,2],205,[1],220,[1],225,[1,0,0,0,1],287,[1],296,[1],336,[1],367,[1],381,[1],400,[1]],"f":1},"deqp_khr_gles3_test_expectations.txt":{"r":[239,[1],272,[1],287,[1],323,[1,0,0,2],335,[1,1,0,1],343,[1,0,0,1,2,1],353,[1,0,1],381,[1,1],393,[1]],"f":1},"deqp_gles31_multisample_test_expectations.txt":{"r":[300,[2],322,[1],382,[1]],"f":1},"angle_deqp_libtester_main.cpp":{"r":[0,[1],70,[1],88,[3,0,0,0,1],100,[1],134,[1],150,[1,0,2],205,[1],229,[1],323,[1],367,[1],381,[1]],"f":1},"deqp_khr_gles32_test_expectations.txt":{"r":[239,[1,1],272,[1],287,[1],292,[1],309,[1],322,[1,1,0,0,2],335,[1,0,0,1],343,[1],349,[3,0,0,0,1],367,[1,0,0,1],381,[1]],"f":1},"tcuRandomOrderExecutor.cpp":{"r":[0,[1],70,[1],205,[1],336,[1],381,[1]],"f":1},"tcuRandomOrderExecutor.h":{"r":[0,[1],70,[1],205,[1],381,[1]],"f":1},"angle_deqp_libtester.h":{"r":[0,[1],70,[1],88,[3],150,[1,0,2],205,[1],367,[1]],"f":1},"tcuANGLENativeDisplayFactory.h":{"r":[0,[1],70,[1],134,[1],367,[1]],"f":1},"tcuANGLEPlatform.cpp":{"r":[0,[1],70,[1],92,[1],107,[2,2,1],134,[1],150,[1,0,2],205,[1],225,[1],240,[1],287,[1],344,[2],367,[1]],"f":1},"tcuANGLEPlatform.h":{"r":[0,[1],70,[1],134,[1],150,[1,0,2],205,[1],240,[1],367,[1]],"f":1},"deqp_gl46_test_expectations.txt":{"r":[242,[1,0,0,1],326,[2,0,0,1],335,[1,1,0,1],343,[1,0,0,0,2,1],353,[1]],"d":1728462892000,"f":1},"glcTestPackageEntry_override.cpp":{"r":[88,[3],242,[1],292,[1],353,[1]],"f":1},"BUILD.gn":{"r":[100,[1],107,[2,2,1],118,[1,0,0,0,1,1],205,[1],216,[1],240,[1],329,[1],343,[1]],"f":1},"deqp_data_autogen.gni":{"r":[100,[1],107,[2,2,1],205,[1],216,[1],240,[1,0,1,0,0,1],329,[1],343,[1]],"f":1},"deqp_gles31_rotate_test_expectations.txt":{"r":[239,[1],287,[1],338,[1],343,[1]],"f":1},"deqp_khr_gles2_test_expectations.txt":{"r":[239,[1],305,[1],323,[1],338,[1],343,[1]],"f":1},"deqp_gles3_rotate_test_expectations.txt":{"r":[239,[1],296,[1],338,[1]],"f":1},"tes31Context_override.cpp":{"r":[88,[3,0,0,0,1],100,[1],107,[2,2,1],205,[1],216,[1],336,[1]],"d":1718351653000,"f":1},"README.md":{"r":[134,[1],150,[1,0,2],205,[1],216,[1],321,[1]],"f":1},"deqp_gles31_565-no-depth-no-stencil_test_expectations.txt":{"r":[302,[1,1]],"d":1698329175000,"f":1},"deqp_gles31_565_no_depth_no_stencil_test_expectations.txt":{"r":[300,[1,0,1,1]],"f":1},"deqp_gles3_565-no-depth-no-stencil_test_expectations.txt":{"r":[302,[1,1]],"d":1698329175000,"f":1},"deqp_gles3_565_no_depth_no_stencil_test_expectations.txt":{"r":[300,[1,0,1,1]],"f":1},"deqp_gles3_multisample_test_expectations.txt":{"r":[300,[2]],"f":1},"deqp_khr_noctx_gles2_test_expectations.txt":{"r":[292,[1]],"f":1},"deqp_khr_noctx_gles32_test_expectations.txt":{"r":[292,[1]],"f":1},"deqp_khr_single_gles32_test_expectations.txt":{"r":[292,[1]],"f":1},"deqp_egl_TestExpectations":{"r":[0,[1],70,[1],88,[3,0,0,0,1],100,[1],107,[2,2,1],124,[1],134,[1],150,[1,0,2],205,[1],216,[1,0,0,0,1,0,1],229,[1],234,[1],239,[1]],"d":1659427235000,"f":1},"deqp_gles2_TestExpectations":{"r":[0,[1],70,[1],88,[3,0,0,0,1],100,[1],107,[2,2,1],134,[1],150,[1,0,2],205,[1],216,[1,0,0,0,1,0,1,0,0,1,0,0,0,1],234,[1],239,[1]],"d":1659427235000,"f":1},"deqp_gles31_TestExpectations":{"r":[0,[1],70,[1],88,[3,0,0,0,1],100,[1],107,[2,2,1],118,[1,0,0,0,1,1,1],134,[1],150,[1,0,2],205,[1],216,[1,0,0,0,1,0,1,0,0,1,0,0,0,1],234,[1],239,[1]],"d":1659427235000,"f":1},"deqp_gles31_rotate_TestExpectations":{"r":[150,[1,0,2],205,[1],216,[1],239,[1]],"d":1659427235000,"f":1},"deqp_gles3_TestExpectations":{"r":[0,[1],70,[1],88,[3,0,0,0,1],100,[1],107,[2,2,1],118,[1,0,0,0,1,1],134,[1],150,[1,0,2],205,[1],216,[1,0,0,0,1,0,1,0,0,1],234,[1],239,[1]],"d":1659427235000,"f":1},"deqp_gles3_rotate_TestExpectations":{"r":[150,[1,0,2],220,[1],239,[1]],"d":1659427235000,"f":1},"deqp_khr_gles2_TestExpectations":{"r":[88,[3,0,0,0,1],100,[1],134,[1],205,[1],220,[1],239,[1]],"d":1659427235000,"f":1},"deqp_khr_gles31_TestExpectations":{"r":[88,[3,0,0,0,1],100,[1],107,[2,2,1],118,[1,0,0,0,1,1,1],134,[1],205,[1],216,[1,0,0,0,1,0,1,0,0,1,0,0,0,1],234,[1],239,[1]],"d":1659427235000,"f":1},"deqp_khr_gles32_TestExpectations":{"r":[205,[1],216,[1,0,0,0,1],239,[1]],"d":1659427235000,"f":1},"deqp_khr_gles3_TestExpectations":{"r":[88,[3,0,0,0,1],100,[1],124,[1],134,[1],205,[1],216,[1,0,0,0,1,0,1],239,[1]],"d":1659427235000,"f":1},"glcShaderConstExprTests_override.cpp":{"r":[100,[1],205,[1]],"d":1638906696000,"f":1},"glcShaderMacroTests_override.cpp":{"r":[100,[1],150,[1,0,2]],"d":1606934161000,"f":1},"egluNativeDisplay_override.cpp":{"r":[70,[1],88,[3]],"d":1568336399000,"f":1},"egluNativeDisplay_override.hpp":{"r":[70,[1],88,[3]],"d":1568336399000,"f":1},"egluUtil_override.cpp":{"r":[70,[1],88,[3]],"d":1568336399000,"f":1},"angle_deqp_gtest_main.cpp":{"r":[0,[1],70,[1]],"d":1557375346000,"f":1},"es2fShaderMatrixTests.cpp":{"r":[0,[1],70,[1]],"d":1557375346000,"f":1},"es3fShaderMatrixTests.cpp":{"r":[0,[1],70,[1]],"d":1557375346000,"f":1},"qpTestLog.c":{"r":[0,[1],70,[1]],"d":1557375346000,"f":1},"angle_deqp_tests_main.cpp":{"r":[0,[1]],"f":1}},"LayoutTests/platform/mac-tahoe-wk2-pixel/imported/w3c/web-platform-tests/svg/pservers":{"reftests":{"r":[418,[1]]}},"LayoutTests/platform/mac-wk1/imported/w3c/web-platform-tests/html/semantics/scripting-1":{"the-script-element":{"r":[94,[1,1],102,[1],114,[1],125,[1],142,[1],182,[2],213,[1],238,[1],396,[1],401,[1],418,[1]],"d":1767809910000}},"Source/WebCore/accessibility/playstation":{"AXObjectCachePlayStation.cpp":{"r":[311,[1,0,0,1],328,[1,0,0,1,2],347,[1],356,[1,0,0,0,3],367,[1],388,[1],397,[1,0,0,0,1,0,0,2],409,[1]],"f":1},"AccessibilityObjectPlayStation.cpp":{"r":[311,[1,0,0,1],397,[1]],"f":1}},"JSTests/test262/test/built-ins/DataView/prototype":{"setBigInt64":{"r":[4,[1],13,[1],18,[1],145,[1],183,[1],328,[1],404,[1]]},"setBigUint64":{"r":[145,[1],183,[1],328,[1],404,[1]]},"setFloat16":{"r":[328,[1],389,[1],404,[1]]},"setFloat32":{"r":[0,[1,0,0,0,1],91,[1],145,[1],183,[1],328,[1],404,[1]]},"setFloat64":{"r":[0,[1,0,0,0,1],91,[1],145,[1],183,[1],328,[1],404,[1]]},"setInt16":{"r":[0,[1,0,0,0,1],91,[1],145,[1],183,[1],328,[1],404,[1]]},"setInt32":{"r":[0,[1,0,0,0,1],13,[1],91,[1],145,[1],183,[1],328,[1],404,[1]]},"setInt8":{"r":[0,[1,0,0,0,1],91,[1],145,[1],183,[1],328,[1],404,[1]]},"setUint16":{"r":[0,[1,0,0,0,1],91,[1],145,[1],183,[1],328,[1],404,[1]]},"setUint32":{"r":[0,[1,0,0,0,1],91,[1],145,[1],183,[1],328,[1],404,[1]]},"setUint8":{"r":[0,[1,0,0,0,1],91,[1],145,[1],183,[1],328,[1],404,[1]]},"getFloat16":{"r":[328,[1],389,[1]]},"Symbol.toStringTag.js":{"r":[0,[1,0,0,0,1],91,[1],194,[1],359,[1]],"f":1},"getInt16":{"r":[0,[1,0,0,0,1],91,[1],145,[1],183,[1],328,[1],359,[1]]},"buffer":{"r":[0,[1,0,0,0,1],91,[1],328,[1]]},"byteLength":{"r":[0,[1,0,0,0,1],91,[1],145,[1],183,[1],201,[1],328,[1]]},"byteOffset":{"r":[0,[1,0,0,0,1],91,[1],183,[1],201,[1],328,[1]]},"getBigInt64":{"r":[4,[1],13,[1],145,[1],183,[1],328,[1]]},"getBigUint64":{"r":[4,[1],13,[1],145,[1],183,[1],328,[1]]},"getFloat32":{"r":[0,[1,0,0,0,1],91,[1],145,[1],183,[1],328,[1]]},"getFloat64":{"r":[0,[1,0,0,0,1],91,[1],145,[1],183,[1],328,[1]]},"getInt32":{"r":[0,[1,0,0,0,1],91,[1],145,[1],183,[1],328,[1]]},"getInt8":{"r":[0,[1,0,0,0,1],91,[1],145,[1],183,[1],328,[1]]},"getUint16":{"r":[0,[1,0,0,0,1],91,[1],145,[1],183,[1],328,[1]]},"getUint32":{"r":[0,[1,0,0,0,1],91,[1],145,[1],183,[1],328,[1]]},"getUint8":{"r":[0,[1,0,0,0,1],91,[1],145,[1],183,[1],328,[1]]}},"LayoutTests/imported/w3c/web-platform-tests/mixed-content/gen/sharedworker-classic-data.http-rp":{"opt-in":{"r":[240,[1],399,[1]]}},"LayoutTests/imported/tc39-tg4/source-map-tests/resources":{"basic-mapping-as-index-map.js":{"r":[383,[1]],"f":1},"basic-mapping-as-index-map.js.map":{"r":[383,[1]],"f":1},"basic-mapping-original.js":{"r":[383,[1]],"f":1},"basic-mapping.js":{"r":[383,[1]],"f":1},"basic-mapping.js.map":{"r":[383,[1]],"f":1},"file-not-a-string-1.js":{"r":[383,[1]],"f":1},"file-not-a-string-1.js.map":{"r":[383,[1]],"f":1},"file-not-a-string-2.js":{"r":[383,[1]],"f":1},"file-not-a-string-2.js.map":{"r":[383,[1]],"f":1},"ignore-list-empty.js":{"r":[383,[1]],"f":1},"ignore-list-empty.js.map":{"r":[383,[1]],"f":1},"ignore-list-out-of-bounds-1.js":{"r":[383,[1]],"f":1},"ignore-list-out-of-bounds-1.js.map":{"r":[383,[1]],"f":1},"ignore-list-out-of-bounds-2.js":{"r":[383,[1]],"f":1},"ignore-list-out-of-bounds-2.js.map":{"r":[383,[1]],"f":1},"ignore-list-valid-1.js":{"r":[383,[1]],"f":1},"ignore-list-valid-1.js.map":{"r":[383,[1]],"f":1},"ignore-list-wrong-type-1.js":{"r":[383,[1]],"f":1},"ignore-list-wrong-type-1.js.map":{"r":[383,[1]],"f":1},"ignore-list-wrong-type-2.js":{"r":[383,[1]],"f":1},"ignore-list-wrong-type-2.js.map":{"r":[383,[1]],"f":1},"ignore-list-wrong-type-3.js":{"r":[383,[1]],"f":1},"ignore-list-wrong-type-3.js.map":{"r":[383,[1]],"f":1},"ignore-list-wrong-type-4.js":{"r":[383,[1]],"f":1},"ignore-list-wrong-type-4.js.map":{"r":[383,[1]],"f":1},"index-map-empty-sections.js":{"r":[383,[1]],"f":1},"index-map-empty-sections.js.map":{"r":[383,[1]],"f":1},"index-map-file-wrong-type-1.js":{"r":[383,[1]],"f":1},"index-map-file-wrong-type-1.js.map":{"r":[383,[1]],"f":1},"index-map-file-wrong-type-2.js":{"r":[383,[1]],"f":1},"index-map-file-wrong-type-2.js.map":{"r":[383,[1]],"f":1},"index-map-invalid-base-mappings.js":{"r":[383,[1]],"f":1},"index-map-invalid-base-mappings.js.map":{"r":[383,[1]],"f":1},"index-map-invalid-order.js":{"r":[383,[1]],"f":1},"index-map-invalid-order.js.map":{"r":[383,[1]],"f":1},"index-map-invalid-overlap.js":{"r":[383,[1]],"f":1},"index-map-invalid-overlap.js.map":{"r":[383,[1]],"f":1},"index-map-invalid-sub-map.js":{"r":[383,[1]],"f":1},"index-map-invalid-sub-map.js.map":{"r":[383,[1]],"f":1},"index-map-missing-file.js":{"r":[383,[1]],"f":1},"index-map-missing-file.js.map":{"r":[383,[1]],"f":1},"index-map-missing-map.js":{"r":[383,[1]],"f":1},"index-map-missing-map.js.map":{"r":[383,[1]],"f":1},"index-map-missing-offset-column.js":{"r":[383,[1]],"f":1},"index-map-missing-offset-column.js.map":{"r":[383,[1]],"f":1},"index-map-missing-offset-line.js":{"r":[383,[1]],"f":1},"index-map-missing-offset-line.js.map":{"r":[383,[1]],"f":1},"index-map-missing-offset.js":{"r":[383,[1]],"f":1},"index-map-missing-offset.js.map":{"r":[383,[1]],"f":1},"index-map-offset-column-wrong-type.js":{"r":[383,[1]],"f":1},"index-map-offset-column-wrong-type.js.map":{"r":[383,[1]],"f":1},"index-map-offset-line-wrong-type.js":{"r":[383,[1]],"f":1},"index-map-offset-line-wrong-type.js.map":{"r":[383,[1]],"f":1},"index-map-two-concatenated-sources.js":{"r":[383,[1]],"f":1},"index-map-two-concatenated-sources.js.map":{"r":[383,[1]],"f":1},"index-map-wrong-type-map.js":{"r":[383,[1]],"f":1},"index-map-wrong-type-map.js.map":{"r":[383,[1]],"f":1},"index-map-wrong-type-offset.js":{"r":[383,[1]],"f":1},"index-map-wrong-type-offset.js.map":{"r":[383,[1]],"f":1},"index-map-wrong-type-sections.js":{"r":[383,[1]],"f":1},"index-map-wrong-type-sections.js.map":{"r":[383,[1]],"f":1},"invalid-mapping-bad-separator.js":{"r":[383,[1]],"f":1},"invalid-mapping-bad-separator.js.map":{"r":[383,[1]],"f":1},"invalid-mapping-not-a-string-1.js":{"r":[383,[1]],"f":1},"invalid-mapping-not-a-string-1.js.map":{"r":[383,[1]],"f":1},"invalid-mapping-not-a-string-2.js":{"r":[383,[1]],"f":1},"invalid-mapping-not-a-string-2.js.map":{"r":[383,[1]],"f":1},"invalid-mapping-segment-column-too-large.js":{"r":[383,[1]],"f":1},"invalid-mapping-segment-column-too-large.js.map":{"r":[383,[1]],"f":1},"invalid-mapping-segment-name-index-out-of-bounds.js":{"r":[383,[1]],"f":1},"invalid-mapping-segment-name-index-out-of-bounds.js.map":{"r":[383,[1]],"f":1},"invalid-mapping-segment-name-index-too-large.js":{"r":[383,[1]],"f":1},"invalid-mapping-segment-name-index-too-large.js.map":{"r":[383,[1]],"f":1},"invalid-mapping-segment-negative-column.js":{"r":[383,[1]],"f":1},"invalid-mapping-segment-negative-column.js.map":{"r":[383,[1]],"f":1},"invalid-mapping-segment-negative-name-index.js":{"r":[383,[1]],"f":1},"invalid-mapping-segment-negative-name-index.js.map":{"r":[383,[1]],"f":1},"invalid-mapping-segment-negative-original-column.js":{"r":[383,[1]],"f":1},"invalid-mapping-segment-negative-original-column.js.map":{"r":[383,[1]],"f":1},"invalid-mapping-segment-negative-original-line.js":{"r":[383,[1]],"f":1},"invalid-mapping-segment-negative-original-line.js.map":{"r":[383,[1]],"f":1},"invalid-mapping-segment-negative-relative-column.js":{"r":[383,[1]],"f":1},"invalid-mapping-segment-negative-relative-column.js.map":{"r":[383,[1]],"f":1},"invalid-mapping-segment-negative-relative-name-index.js":{"r":[383,[1]],"f":1},"invalid-mapping-segment-negative-relative-name-index.js.map":{"r":[383,[1]],"f":1},"invalid-mapping-segment-negative-relative-original-column.js":{"r":[383,[1]],"f":1},"invalid-mapping-segment-negative-relative-original-column.js.map":{"r":[383,[1]],"f":1},"invalid-mapping-segment-negative-relative-original-line.js":{"r":[383,[1]],"f":1},"invalid-mapping-segment-negative-relative-original-line.js.map":{"r":[383,[1]],"f":1},"invalid-mapping-segment-negative-relative-source-index.js":{"r":[383,[1]],"f":1},"invalid-mapping-segment-negative-relative-source-index.js.map":{"r":[383,[1]],"f":1},"invalid-mapping-segment-negative-source-index.js":{"r":[383,[1]],"f":1},"invalid-mapping-segment-negative-source-index.js.map":{"r":[383,[1]],"f":1},"invalid-mapping-segment-original-column-too-large.js":{"r":[383,[1]],"f":1},"invalid-mapping-segment-original-column-too-large.js.map":{"r":[383,[1]],"f":1},"invalid-mapping-segment-original-line-too-large.js":{"r":[383,[1]],"f":1},"invalid-mapping-segment-original-line-too-large.js.map":{"r":[383,[1]],"f":1},"invalid-mapping-segment-source-index-out-of-bounds.js":{"r":[383,[1]],"f":1},"invalid-mapping-segment-source-index-out-of-bounds.js.map":{"r":[383,[1]],"f":1},"invalid-mapping-segment-source-index-too-large.js":{"r":[383,[1]],"f":1},"invalid-mapping-segment-source-index-too-large.js.map":{"r":[383,[1]],"f":1},"invalid-mapping-segment-with-three-fields.js":{"r":[383,[1]],"f":1},"invalid-mapping-segment-with-three-fields.js.map":{"r":[383,[1]],"f":1},"invalid-mapping-segment-with-two-fields.js":{"r":[383,[1]],"f":1},"invalid-mapping-segment-with-two-fields.js.map":{"r":[383,[1]],"f":1},"invalid-mapping-segment-with-zero-fields.js":{"r":[383,[1]],"f":1},"invalid-mapping-segment-with-zero-fields.js.map":{"r":[383,[1]],"f":1},"invalid-vlq-missing-continuation.js":{"r":[383,[1]],"f":1},"invalid-vlq-missing-continuation.js.map":{"r":[383,[1]],"f":1},"invalid-vlq-non-base64-char-padding.js":{"r":[383,[1]],"f":1},"invalid-vlq-non-base64-char-padding.js.map":{"r":[383,[1]],"f":1},"invalid-vlq-non-base64-char.js":{"r":[383,[1]],"f":1},"invalid-vlq-non-base64-char.js.map":{"r":[383,[1]],"f":1},"mapping-semantics-column-reset.js":{"r":[383,[1]],"f":1},"mapping-semantics-column-reset.js.map":{"r":[383,[1]],"f":1},"mapping-semantics-five-field-segment.js":{"r":[383,[1]],"f":1},"mapping-semantics-five-field-segment.js.map":{"r":[383,[1]],"f":1},"mapping-semantics-four-field-segment.js":{"r":[383,[1]],"f":1},"mapping-semantics-four-field-segment.js.map":{"r":[383,[1]],"f":1},"mapping-semantics-relative-1.js":{"r":[383,[1]],"f":1},"mapping-semantics-relative-1.js.map":{"r":[383,[1]],"f":1},"mapping-semantics-relative-2.js":{"r":[383,[1]],"f":1},"mapping-semantics-relative-2.js.map":{"r":[383,[1]],"f":1},"mapping-semantics-single-field-segment.js":{"r":[383,[1]],"f":1},"mapping-semantics-single-field-segment.js.map":{"r":[383,[1]],"f":1},"mappings-missing.js":{"r":[383,[1]],"f":1},"mappings-missing.js.map":{"r":[383,[1]],"f":1},"names-missing.js":{"r":[383,[1]],"f":1},"names-missing.js.map":{"r":[383,[1]],"f":1},"names-not-a-list-1.js":{"r":[383,[1]],"f":1},"names-not-a-list-1.js.map":{"r":[383,[1]],"f":1},"names-not-a-list-2.js":{"r":[383,[1]],"f":1},"names-not-a-list-2.js.map":{"r":[383,[1]],"f":1},"names-not-string.js":{"r":[383,[1]],"f":1},"names-not-string.js.map":{"r":[383,[1]],"f":1},"proposals":{"r":[383,[1]]},"second-source-original.js":{"r":[383,[1]],"f":1},"source-resolution-absolute-url.js":{"r":[383,[1]],"f":1},"source-resolution-absolute-url.js.map":{"r":[383,[1]],"f":1},"source-root-not-a-string-1.js":{"r":[383,[1]],"f":1},"source-root-not-a-string-1.js.map":{"r":[383,[1]],"f":1},"source-root-not-a-string-2.js":{"r":[383,[1]],"f":1},"source-root-not-a-string-2.js.map":{"r":[383,[1]],"f":1},"source-root-resolution.js":{"r":[383,[1]],"f":1},"source-root-resolution.js.map":{"r":[383,[1]],"f":1},"sources-and-sources-content-both-null.js":{"r":[383,[1]],"f":1},"sources-and-sources-content-both-null.js.map":{"r":[383,[1]],"f":1},"sources-content-missing.js":{"r":[383,[1]],"f":1},"sources-content-missing.js.map":{"r":[383,[1]],"f":1},"sources-content-not-a-list-1.js":{"r":[383,[1]],"f":1},"sources-content-not-a-list-1.js.map":{"r":[383,[1]],"f":1},"sources-content-not-a-list-2.js":{"r":[383,[1]],"f":1},"sources-content-not-a-list-2.js.map":{"r":[383,[1]],"f":1},"sources-content-not-string-or-null.js":{"r":[383,[1]],"f":1},"sources-content-not-string-or-null.js.map":{"r":[383,[1]],"f":1},"sources-missing.js":{"r":[383,[1]],"f":1},"sources-missing.js.map":{"r":[383,[1]],"f":1},"sources-non-null-sources-content-null.js":{"r":[383,[1]],"f":1},"sources-non-null-sources-content-null.js.map":{"r":[383,[1]],"f":1},"sources-not-a-list-1.js":{"r":[383,[1]],"f":1},"sources-not-a-list-1.js.map":{"r":[383,[1]],"f":1},"sources-not-a-list-2.js":{"r":[383,[1]],"f":1},"sources-not-a-list-2.js.map":{"r":[383,[1]],"f":1},"sources-not-string-or-null.js":{"r":[383,[1]],"f":1},"sources-not-string-or-null.js.map":{"r":[383,[1]],"f":1},"sources-null-sources-content-non-null.js":{"r":[383,[1]],"f":1},"sources-null-sources-content-non-null.js.map":{"r":[383,[1]],"f":1},"transitive-mapping-original.js":{"r":[383,[1]],"f":1},"transitive-mapping-original.js.map":{"r":[383,[1]],"f":1},"transitive-mapping-three-steps.js":{"r":[383,[1]],"f":1},"transitive-mapping-three-steps.js.map":{"r":[383,[1]],"f":1},"transitive-mapping.js":{"r":[383,[1]],"f":1},"transitive-mapping.js.map":{"r":[383,[1]],"f":1},"typescript-original.ts":{"r":[383,[1]],"f":1},"unrecognized-property.js":{"r":[383,[1]],"f":1},"unrecognized-property.js.map":{"r":[383,[1]],"f":1},"valid-mapping-boundary-values.js":{"r":[383,[1]],"f":1},"valid-mapping-boundary-values.js.map":{"r":[383,[1]],"f":1},"valid-mapping-empty-groups.js":{"r":[383,[1]],"f":1},"valid-mapping-empty-groups.js.map":{"r":[383,[1]],"f":1},"valid-mapping-empty-string.js":{"r":[383,[1]],"f":1},"valid-mapping-empty-string.js.map":{"r":[383,[1]],"f":1},"valid-mapping-large-vlq.js":{"r":[383,[1]],"f":1},"valid-mapping-large-vlq.js.map":{"r":[383,[1]],"f":1},"version-missing.js":{"r":[383,[1]],"f":1},"version-missing.js.map":{"r":[383,[1]],"f":1},"version-not-a-number.js":{"r":[383,[1]],"f":1},"version-not-a-number.js.map":{"r":[383,[1]],"f":1},"version-numeric-string.js":{"r":[383,[1]],"f":1},"version-numeric-string.js.map":{"r":[383,[1]],"f":1},"version-too-high.js":{"r":[383,[1]],"f":1},"version-too-high.js.map":{"r":[383,[1]],"f":1},"version-too-low.js":{"r":[383,[1]],"f":1},"version-too-low.js.map":{"r":[383,[1]],"f":1},"version-valid.js":{"r":[383,[1]],"f":1},"version-valid.js.map":{"r":[383,[1]],"f":1},"vlq-valid-continuation-bit-present-1.js":{"r":[383,[1]],"f":1},"vlq-valid-continuation-bit-present-1.js.map":{"r":[383,[1]],"f":1},"vlq-valid-continuation-bit-present-2.js":{"r":[383,[1]],"f":1},"vlq-valid-continuation-bit-present-2.js.map":{"r":[383,[1]],"f":1},"vlq-valid-negative-digit.js":{"r":[383,[1]],"f":1},"vlq-valid-negative-digit.js.map":{"r":[383,[1]],"f":1},"vlq-valid-single-digit.js":{"r":[383,[1]],"f":1},"vlq-valid-single-digit.js.map":{"r":[383,[1]],"f":1}},"WebDriverTests/imported/selenium/common/src/web/locators_tests":{"locators.html":{"r":[367,[1]],"f":1},"boolean_attribute_selected.html":{"r":[0,[1]],"f":1},"boolean_attribute_selected_html4.html":{"r":[0,[1]],"f":1}},"Source/ThirdParty/skia/src/gpu/ganesh/gl/android":{"BUILD.bazel":{"r":[318,[1],332,[1],345,[1],353,[1]],"f":1},"GrGLMakeNativeInterface_android.cpp":{"r":[318,[1]],"f":1}},"LayoutTests/platform/mac-sonoma-wk2-pixel/imported/w3c/web-platform-tests/svg/linking":{"reftests":{"r":[317,[1],344,[1]],"d":1723336083000}},"PerformanceTests/JetStream3/wasm/argon2":{"CMakeLists.txt":{"r":[344,[1]],"f":1},"README.md":{"r":[344,[1]],"f":1},"argon2":{"r":[344,[1]]},"build-wasm.sh":{"r":[344,[1]],"f":1},"build.sh":{"r":[344,[1]],"f":1},"clean-cmake.sh":{"r":[344,[1]],"f":1},"emcc_version.txt":{"r":[344,[1]],"f":1},"src":{"r":[344,[1]]}},"JSTests/test262/test/built-ins/Temporal/PlainDateTime/prototype/weekOfYear":{"basic.js":{"r":[226,[1],341,[1]],"f":1},"builtin-calendar-no-observable-calls.js":{"r":[288,[1],341,[1]],"d":1721326308000,"f":1},"custom-calendar-weekofyear.js":{"r":[328,[1],341,[1]],"d":1721326308000,"f":1},"custom.js":{"r":[233,[1],254,[1],341,[1]],"d":1721326308000,"f":1},"validate-calendar-value.js":{"r":[254,[1],269,[1],328,[1],341,[1]],"d":1721326308000,"f":1},"prop-desc.js":{"r":[196,[1]],"f":1},"branding.js":{"r":[190,[1]],"f":1}},"LayoutTests/platform/gtk/media/modern-media-controls/media-controller":{"media-controller-auto-hide-pause-expected.txt":{"r":[314,[1],325,[1]],"d":1711538604000,"f":1}},"Websites/browserbench.org/Speedometer3.0-preview/resources/todomvc/architecture-examples/react/src/todo/components":{"footer.jsx":{"r":[319,[1,0,0,1]],"d":1709765028000,"f":1},"header.jsx":{"r":[319,[1,0,0,1]],"d":1709765028000,"f":1},"input.jsx":{"r":[319,[1,0,0,1]],"d":1709765028000,"f":1},"item.jsx":{"r":[319,[1,0,0,1]],"d":1709765028000,"f":1},"main.jsx":{"r":[319,[1,0,0,1]],"d":1709765028000,"f":1}},"LayoutTests/fast/preloader":{"image-in-nested-template-01-expected.txt":{"r":[281,[1]],"f":1},"image-in-nested-template-01.html":{"r":[281,[1]],"f":1},"image-with-incorrect-tag-expected.txt":{"r":[281,[1]],"f":1},"image-with-incorrect-tag.html":{"r":[281,[1]],"f":1},"image-in-nested-template-expected.txt":{"r":[279,[1]],"f":1},"image-in-nested-template.html":{"r":[279,[1]],"f":1},"document-write-2-expected.txt":{"r":[0,[1],142,[1]],"f":1},"document-write-expected.txt":{"r":[0,[1],142,[1]],"f":1},"document-write-noscript-expected.txt":{"r":[0,[1],142,[1]],"f":1},"iframe-srcdoc-expected.txt":{"r":[0,[1],18,[1],118,[1],142,[1]],"f":1},"document-write-2.html":{"r":[0,[1]],"f":1},"document-write-noscript.html":{"r":[0,[1]],"f":1},"document-write.html":{"r":[0,[1]],"f":1},"first-base-tag-scanned-wins-expected.txt":{"r":[0,[1]],"f":1},"first-base-tag-scanned-wins.html":{"r":[0,[1]],"f":1},"first-base-tag-wins-expected.txt":{"r":[0,[1]],"f":1},"first-base-tag-wins.html":{"r":[0,[1]],"f":1},"iframe-srcdoc.html":{"r":[0,[1]],"f":1},"image-data-url-expected.txt":{"r":[0,[1]],"f":1},"image-data-url.html":{"r":[0,[1]],"f":1},"image-expected.txt":{"r":[0,[1]],"f":1},"image-srcset-expected.txt":{"r":[0,[1]],"f":1},"image-srcset.html":{"r":[0,[1]],"f":1},"image.html":{"r":[0,[1]],"f":1},"input-expected.txt":{"r":[0,[1]],"f":1},"input.html":{"r":[0,[1]],"f":1},"link-expected.txt":{"r":[0,[1]],"f":1},"link.html":{"r":[0,[1]],"f":1},"noscript-expected.txt":{"r":[0,[1]],"f":1},"noscript.html":{"r":[0,[1]],"f":1},"resources":{"r":[0,[1]]},"scan-body-from-head-import-expected.txt":{"r":[0,[1]],"f":1},"scan-body-from-head-import.html":{"r":[0,[1]],"f":1},"scan-body-from-head-script-expected.txt":{"r":[0,[1]],"f":1},"scan-body-from-head-script.html":{"r":[0,[1]],"f":1},"script.html":{"r":[0,[1]],"f":1},"style-expected.txt":{"r":[0,[1]],"f":1},"style.html":{"r":[0,[1]],"f":1},"understands-base-tag-expected.txt":{"r":[0,[1]],"f":1},"understands-base-tag.html":{"r":[0,[1]],"f":1}},"JSTests/test262/test/language/statements/class/elements/gen-private-method-static":{"yield-identifier-spread-strict.js":{"r":[56,[1],256,[1]],"f":1},"yield-identifier-strict.js":{"r":[56,[1],256,[1]],"f":1},"yield-spread-arr-multiple.js":{"r":[56,[1],196,[1],256,[1]],"f":1},"yield-spread-arr-single.js":{"r":[56,[1],256,[1]],"f":1},"yield-spread-obj.js":{"r":[56,[1],91,[1],256,[1]],"f":1},"yield-as-binding-identifier-escaped.js":{"r":[56,[1]],"f":1},"yield-as-binding-identifier.js":{"r":[56,[1]],"f":1},"yield-as-identifier-reference-escaped.js":{"r":[56,[1]],"f":1},"yield-as-identifier-reference.js":{"r":[56,[1]],"f":1},"yield-as-label-identifier-escaped.js":{"r":[56,[1]],"f":1},"yield-as-label-identifier.js":{"r":[56,[1]],"f":1}},"WebKitLibraries/WebKitPrivateFrameworkStubs/watchos/6/RunningBoardServices.framework":{"RunningBoardServices.tbd":{"r":[126,[1,1],132,[1],245,[1]],"d":1663093001000,"f":1}},"Source/ThirdParty/libwebrtc/Source/webrtc/resources/audio_processing/agc2":{"rnn_vad":{"r":[33,[1],97,[1],117,[1],179,[3]]}},"LayoutTests/imported/blink/http/tests/xmlhttprequest/workers":{"resources":{"r":[0,[1],176,[1]],"d":1621606887000}},"LayoutTests/imported/w3c/web-platform-tests/referrer-policy/no-referrer-when-downgrade/http-rp/cross-origin/http-http/a-tag/no-redirect":{"insecure-protocol.http-expected.txt":{"r":[70,[1],142,[1]],"f":1},"insecure-protocol.http.html":{"r":[70,[1]],"f":1},"insecure-protocol.http.html.headers":{"r":[70,[1]],"f":1},"w3c-import.log":{"r":[70,[1]],"f":1}},"LayoutTests/imported/w3c/web-platform-tests/referrer-policy/origin-when-cross-origin/attr-referrer/cross-origin/http-https/img-tag/no-redirect":{"cross-origin.http-expected.txt":{"r":[70,[1],142,[1]],"f":1},"cross-origin.http.html":{"r":[70,[1]],"f":1},"w3c-import.log":{"r":[70,[1]],"f":1}},"LayoutTests/imported/w3c/web-platform-tests/referrer-policy/origin/attr-referrer/cross-origin/http-http/img-tag/no-redirect":{"generic.http-expected.txt":{"r":[70,[1],142,[1]],"f":1},"generic.http.html":{"r":[70,[1]],"f":1},"w3c-import.log":{"r":[70,[1]],"f":1}},"PerformanceTests/StitchMarker/wtf/text/icu":{"TextBreakIteratorICU.h":{"r":[0,[1],84,[1],122,[1]],"d":1588972904000,"f":1},"UTextProvider.cpp":{"r":[0,[1],122,[1]],"d":1588972904000,"f":1},"UTextProvider.h":{"r":[0,[1],122,[1]],"d":1588972904000,"f":1},"UTextProviderLatin1.cpp":{"r":[0,[1],122,[1]],"d":1588972904000,"f":1},"UTextProviderLatin1.h":{"r":[0,[1],122,[1]],"d":1588972904000,"f":1},"UTextProviderUTF16.cpp":{"r":[0,[1],122,[1]],"d":1588972904000,"f":1},"UTextProviderUTF16.h":{"r":[0,[1],122,[1]],"d":1588972904000,"f":1}},"LayoutTests/webgl/1.0.2/conformance/glsl/literals":{"float_literal.vert-expected.txt":{"r":[0,[1],96,[1]],"d":1573009279000,"f":1},"float_literal.vert.html":{"r":[0,[1],96,[1]],"d":1573009279000,"f":1}},"LayoutTests/imported/w3c/web-platform-tests/html/semantics/embedded-content/the-area-element/resources":{"w3c-import.log":{"r":[61,[1]],"f":1},"area-download-click.html":{"r":[14,[1]],"f":1}},"Source/ThirdParty/libwebrtc/Source/resources/video_engine":{"renderStartImage.jpg.sha1":{"r":[0,[1]],"f":1},"renderTimeoutImage.jpg.sha1":{"r":[0,[1]],"f":1}}}