[
 {
  "date": "2021-11-25T11:19:51Z",
  "kind": "review",
  "peers": [
   "mstensho"
  ],
  "additions": 0,
  "deletions": 7,
  "files": 1
 },
 {
  "date": "2020-02-21T09:53:03Z",
  "kind": "review",
  "peers": [
   "fwang"
  ],
  "additions": 46,
  "deletions": 0,
  "files": 1
 },
 {
  "date": "2019-11-06T17:38:11Z",
  "kind": "author",
  "peers": [
   "kojii"
  ],
  "additions": 44,
  "deletions": 11,
  "files": 2
 },
 {
  "date": "2019-10-10T02:55:29Z",
  "kind": "author",
  "peers": [
   "bokan",
   "fwang",
   "jochen"
  ],
  "additions": 319,
  "deletions": 277,
  "files": 50
 },
 {
  "date": "2019-10-09T13:04:18Z",
  "kind": "author",
  "peers": [
   "fwang"
  ],
  "additions": 2,
  "deletions": 2,
  "files": 1
 },
 {
  "date": "2019-10-08T11:19:13Z",
  "kind": "author",
  "peers": [
   "bokan"
  ],
  "additions": 17,
  "deletions": 0,
  "files": 2
 },
 {
  "date": "2019-08-18T18:24:26Z",
  "kind": "author",
  "peers": [
   "kojii"
  ],
  "additions": 33,
  "deletions": 7,
  "files": 2
 },
 {
  "date": "2019-08-14T15:28:01Z",
  "kind": "author",
  "peers": [
   "bokan",
   "fwang"
  ],
  "additions": 251,
  "deletions": 0,
  "files": 4
 },
 {
  "date": "2019-08-10T18:06:58Z",
  "kind": "author",
  "peers": [
   "bokan",
   "fwang"
  ],
  "additions": 151,
  "deletions": 156,
  "files": 13
 },
 {
  "date": "2019-08-03T03:33:56Z",
  "kind": "author",
  "peers": [
   "bokan",
   "fwang"
  ],
  "additions": 95,
  "deletions": 140,
  "files": 13
 },
 {
  "date": "2019-07-16T08:59:25Z",
  "kind": "author",
  "peers": [
   "bokan",
   "fwang"
  ],
  "additions": 16,
  "deletions": 45,
  "files": 6
 },
 {
  "date": "2019-06-27T10:34:16Z",
  "kind": "author",
  "peers": [
   "ikilpatrick",
   "kojii",
   "mstensho"
  ],
  "additions": 251,
  "deletions": 54,
  "files": 7
 },
 {
  "date": "2019-06-17T10:55:18Z",
  "kind": "author",
  "peers": [
   "kojii"
  ],
  "additions": 136,
  "deletions": 0,
  "files": 6
 },
 {
  "date": "2019-04-10T12:37:41Z",
  "kind": "author",
  "peers": [
   "kojii"
  ],
  "additions": 8,
  "deletions": 8,
  "files": 2
 },
 {
  "date": "2019-01-08T04:00:42Z",
  "kind": "author",
  "peers": [
   "fwang",
   "kojii",
   "rbuis",
   "rego"
  ],
  "additions": 237,
  "deletions": 113,
  "files": 27
 },
 {
  "date": "2019-01-03T16:44:10Z",
  "kind": "author",
  "peers": [
   "rego"
  ],
  "additions": 37,
  "deletions": 3,
  "files": 3
 }
]