[
 {
  "date": "2019-06-05T09:28:41Z",
  "kind": "review",
  "peers": [
   "mustaq@google.com"
  ],
  "additions": 52,
  "deletions": 0,
  "files": 1
 },
 {
  "date": "2018-07-04T17:14:18Z",
  "kind": "author",
  "peers": [
   "garykac@chromium.org"
  ],
  "additions": 208,
  "deletions": 8,
  "files": 10
 },
 {
  "date": "2018-05-18T10:15:13Z",
  "kind": "author",
  "peers": [
   "garykac@chromium.org"
  ],
  "additions": 39,
  "deletions": 0,
  "files": 2
 },
 {
  "date": "2018-05-08T14:52:01Z",
  "kind": "author",
  "peers": [
   "garykac@chromium.org"
  ],
  "additions": 67,
  "deletions": 0,
  "files": 3
 },
 {
  "date": "2018-04-20T20:59:28Z",
  "kind": "author",
  "peers": [
   "garykac@chromium.org"
  ],
  "additions": 9,
  "deletions": 11,
  "files": 4
 },
 {
  "date": "2018-04-15T07:35:02Z",
  "kind": "author",
  "peers": [
   "foolip@chromium.org",
   "garykac@chromium.org",
   "dcheng@chromium.org"
  ],
  "additions": 70,
  "deletions": 60,
  "files": 7
 }
]